regis/__init__.py
regis/build.py
regis/code_coverage.py
regis/compiler_db.py
regis/diagnostics.py
regis/dir_watcher.py
regis/generation.py
regis/git.py
regis/git_hooks.py
regis/required_externals.py
regis/required_libs.py
regis/required_tools.py
regis/rex_json.py
regis/run_clang_format.py
regis/run_clang_tidy.py
regis/run_clang_tools.py
regis/subproc.py
regis/task_raii_printing.py
regis/test.py
regis/util.py
regis/vs.py
regis/.vscode/settings.json
regis-0.1.90.dist-info/METADATA
regis-0.1.90.dist-info/WHEEL
regis-0.1.90.dist-info/licenses/LICENSE
regis-0.1.90.dist-info/RECORD
