Metadata-Version: 2.4
Name: regis
Version: 0.1.90
Summary: python framework used by Rex Engine
Project-URL: Homepage, https://github.com/RisingLiberty/RexPy
Project-URL: Bug Tracker, https://github.com/RisingLiberty/RexPy/issues
Author-email: Nick De Breuck <nick.debreuck@outlook.com>
License-File: LICENSE
Classifier: License :: OSI Approved :: MIT License
Classifier: Operating System :: OS Independent
Classifier: Programming Language :: Python :: 3
Requires-Python: >=3.9
Requires-Dist: filelock
Requires-Dist: gitpython
Requires-Dist: psutil
Requires-Dist: requests
Requires-Dist: termcolor>=2.2.0
Requires-Dist: watchdog
